nuad
