Metadata-Version: 2.1
Name: nuad
Version: 0.1.6
Summary: nuad stands for "NUcleic Acid Designer". Enables one to specify constraints on a DNA (or RNA) nanostructure made from synthetic DNA/RNA and then attempts to find concrete DNA sequences that satisfy the constraints.
Home-page: https://github.com/UC-Davis-molecular-computing/nuad
Author: David Doty
Author-email: doty@ucdavis.edu
License: MIT
Platform: UNKNOWN
Requires-Python: >=3.7
License-File: LICENSE
